bot/__init__.py
bot/default.py
bot/encoder.py
bot/objects.py
bot/opqueue.py
bot/storage.py
bot/utility.py
bot/modules/__init__.py
bot/modules/cmd.py
bot/modules/irc.py
bot/modules/rss.py
bot/runtime/__init__.py
bot/runtime/bus.py
bot/runtime/callback.py
bot/runtime/command.py
bot/runtime/config.py
bot/runtime/event.py
bot/runtime/handler.py
bot/runtime/parser.py
bot/runtime/repeater.py
bot/runtime/scanner.py
bot/runtime/thread.py
bot/runtime/timer.py
bot/runtime/utils.py
botlib-202.dist-info/METADATA
botlib-202.dist-info/WHEEL
botlib-202.dist-info/top_level.txt
botlib-202.dist-info/zip-safe
botlib-202.dist-info/RECORD
