Metadata-Version: 2.1
Name: botlib
Version: 202
Summary: The Python3 bot Namespace
Home-page: https://github.com/bthate/botlib
Author: Bart Thate
Author-email: bthate67@gmail.com
License: Public Domain
Platform: UNKNOWN
Classifier: Development Status :: 4 - Beta
Classifier: License :: Public Domain
Classifier: Operating System :: Unix
Classifier: Programming Language :: Python
Classifier: Topic :: Utilities
